Metadata-Version: 2.1
Name: processador-imagem
Version: 0.0.1
Summary: pacote de processamento de imagens
Home-page: https://github.com/UiliamBomfim/package-template
Author: Uiliam bomfim
Author-email: wf3@outlook.com.br
License: UNKNOWN
Platform: UNKNOWN
Requires-Python: >=3.8
Requires-Dist: setuptools
Requires-Dist: scikit-image
Requires-Dist: numpy
Requires-Dist: matplotlib
